README.md
setup.cfg
setup.py
api_cli/__init__.py
api_cli/main.py
api_cli.egg-info/PKG-INFO
api_cli.egg-info/SOURCES.txt
api_cli.egg-info/dependency_links.txt
api_cli.egg-info/entry_points.txt
api_cli.egg-info/requires.txt
api_cli.egg-info/top_level.txt
api_cli.egg-info/zip-safe
api_cli/acts/__init__.py
api_cli/acts/config.py
api_cli/acts/create.py
api_cli/acts/tools.py
api_cli/cmds/__init__.py
api_cli/cmds/config.py
api_cli/cmds/create.py
api_cli/cmds/tools.py
api_cli/cmds/version.py
api_cli/utils/__init__.py
api_cli/utils/base.py
api_cli/utils/helper.py
api_cli/utils/templete.py
tests/__init__.py