Metadata-Version: 1.1
Name: api-cli
Version: 1.0.1
Summary: A tiny and smart cli tool for managing api-frame based on Python.
Home-page: https://gitee.com/dzlua/api-cli.git
Author: dzlua
Author-email: 505544956@qq.com
License: MIT
Keywords: api-cli api-frame api frame cli python
Platform: UNKNOWN
Classifier: Development Status :: 4 - Beta
